csverve/__init__.py
csverve/_version.py
csverve/cli.py
csverve/api/__init__.py
csverve/api/api.py
csverve/core/__init__.py
csverve/core/csverve_input.py
csverve/core/csverve_output.py
csverve/core/csverve_output_data_frame.py
csverve/core/csverve_output_file_stream.py
csverve/core/irregular_csv_input.py
csverve/errors/__init__.py
csverve/errors/errors.py
csverve/utils/__init__.py
csverve/utils/utils.py
csverve-0.3.8.dist-info/AUTHORS.rst
csverve-0.3.8.dist-info/LICENSE
csverve-0.3.8.dist-info/METADATA
csverve-0.3.8.dist-info/WHEEL
csverve-0.3.8.dist-info/entry_points.txt
csverve-0.3.8.dist-info/top_level.txt
csverve-0.3.8.dist-info/RECORD
