Metadata-Version: 2.1
Name: csverve
Version: 0.3.8
Summary: todo: add description
Home-page: https://github.com/mondrian-scwgs/csverve
Author: Shah Lab
Author-email: todo@todo.com
License: MIT license
Keywords: csverve
Platform: UNKNOWN
Classifier: Development Status :: 2 - Pre-Alpha
Classifier: Intended Audience :: Developers
Classifier: License :: OSI Approved :: MIT License
Classifier: Natural Language :: English
Classifier: Programming Language :: Python :: 3
Classifier: Programming Language :: Python :: 3.6
Classifier: Programming Language :: Python :: 3.7
Classifier: Programming Language :: Python :: 3.8
Requires-Python: >=3.6
License-File: LICENSE
License-File: AUTHORS.rst
Requires-Dist: click (>=7.0)
Requires-Dist: pandas (>=1.0.0)
Requires-Dist: pyyaml
Requires-Dist: numpy (<2)
Requires-Dist: pytest
Requires-Dist: Sphinx (==5.1.1)
Requires-Dist: mypy
